torch4nlp/__init__.py
torch4nlp/pretrain_gpt.py
torch4nlp/rm.py
torch4nlp/run_clm.py
torch4nlp/tfidf.py
torch4nlp/unit_test.py
torch4nlp/dsa/__init__.py
torch4nlp/dsa/tree.py
torch4nlp/utils/__init__.py
torch4nlp/utils/file_util.py
torch4nlp/utils/metric_util.py
torch4nlp/utils/text_util.py
torch4nlp/utils/time_utils.py
torch4nlp-0.1.1.dist-info/LICENSE
torch4nlp-0.1.1.dist-info/METADATA
torch4nlp-0.1.1.dist-info/WHEEL
torch4nlp-0.1.1.dist-info/top_level.txt
torch4nlp-0.1.1.dist-info/RECORD
